non_hashing_collections/__init__.py
non_hashing_collections/dict.py
non_hashing_collections-0.1.dev0.dist-info/LICENSE
non_hashing_collections-0.1.dev0.dist-info/WHEEL
non_hashing_collections-0.1.dev0.dist-info/METADATA
non_hashing_collections-0.1.dev0.dist-info/RECORD
