Metadata-Version: 2.1
Name: non-hashing-collections
Version: 0.1.dev0
Summary: Includes implementations of Python collection types that don't require hashability.
Author-email: Kaleb Barrett <dev.ktbarrett@gmail.com>
Requires-Python: >=3.8
Classifier: License :: OSI Approved :: GNU Lesser General Public License v2 (LGPLv2)
Project-URL: Home, https://github.com/ktbarrett/non_hashing_collections/
